gpmf_parser.cpython-311-x86_64-linux-gnu.so
py_gpmf_parser/__init__.py
py_gpmf_parser/gopro_telemetry_extractor.py
py_gpmf_parser-0.1.0.dist-info/METADATA
py_gpmf_parser-0.1.0.dist-info/WHEEL
py_gpmf_parser-0.1.0.dist-info/top_level.txt
py_gpmf_parser-0.1.0.dist-info/RECORD
py_gpmf_parser-0.1.0.dist-info/licenses/LICENSE
