Metadata-Version: 2.4
Name: py_gpmf_parser
Version: 0.1.0
Summary: Python bindings for the gpmf-parser library using pybind
Author-email: Steffen Urban <urbste@gmail.com>
License-Expression: Apache-2.0
Project-URL: Homepage, https://github.com/urbste/py-gpmf-parser
Requires-Python: >=3.8
License-File: LICENSE
Requires-Dist: numpy>=1.24.4
Dynamic: license-file
